githubkit/__init__.py
githubkit/auth/__init__.py
githubkit/auth/_url.py
githubkit/auth/action.py
githubkit/auth/app.py
githubkit/auth/base.py
githubkit/auth/oauth.py
githubkit/auth/token.py
githubkit/auth/unauth.py
githubkit/cache/__init__.py
githubkit/cache/base.py
githubkit/cache/mem_cache.py
githubkit/config.py
githubkit/core.py
githubkit/exception.py
githubkit/github.py
githubkit/graphql/__init__.py
githubkit/graphql/models.py
githubkit/paginator.py
githubkit/py.typed
githubkit/response.py
githubkit/rest/__init__.py
githubkit/rest/actions.py
githubkit/rest/activity.py
githubkit/rest/apps.py
githubkit/rest/billing.py
githubkit/rest/checks.py
githubkit/rest/code_scanning.py
githubkit/rest/codes_of_conduct.py
githubkit/rest/codespaces.py
githubkit/rest/dependabot.py
githubkit/rest/dependency_graph.py
githubkit/rest/emojis.py
githubkit/rest/gists.py
githubkit/rest/git.py
githubkit/rest/gitignore.py
githubkit/rest/interactions.py
githubkit/rest/issues.py
githubkit/rest/licenses.py
githubkit/rest/markdown.py
githubkit/rest/meta.py
githubkit/rest/migrations.py
githubkit/rest/models.py
githubkit/rest/oidc.py
githubkit/rest/orgs.py
githubkit/rest/packages.py
githubkit/rest/projects.py
githubkit/rest/pulls.py
githubkit/rest/rate_limit.py
githubkit/rest/reactions.py
githubkit/rest/repos.py
githubkit/rest/search.py
githubkit/rest/secret_scanning.py
githubkit/rest/security_advisories.py
githubkit/rest/teams.py
githubkit/rest/types.py
githubkit/rest/users.py
githubkit/typing.py
githubkit/utils.py
githubkit/webhooks/__init__.py
githubkit/webhooks/models.py
githubkit/webhooks/parse.py
githubkit/webhooks/types.py
githubkit/webhooks/verify.py
githubkit-0.10.6.dist-info/LICENSE
githubkit-0.10.6.dist-info/METADATA
githubkit-0.10.6.dist-info/WHEEL
githubkit-0.10.6.dist-info/RECORD
