Metadata-Version: 2.1
Name: githubkit
Version: 0.10.6
Summary: GitHub SDK for Python
Home-page: https://github.com/yanyongyu/githubkit
License: MIT
Keywords: github,octokit
Author: yanyongyu
Author-email: yyy@yyydl.top
Requires-Python: >=3.8,<4.0
Classifier: License :: OSI Approved :: MIT License
Classifier: Programming Language :: Python :: 3
Classifier: Programming Language :: Python :: 3.8
Classifier: Programming Language :: Python :: 3.9
Classifier: Programming Language :: Python :: 3.10
Classifier: Programming Language :: Python :: 3.11
Provides-Extra: all
Provides-Extra: auth
Provides-Extra: auth-app
Provides-Extra: auth-oauth-device
Provides-Extra: jwt
Requires-Dist: PyJWT[crypto] (>=2.4.0,<3.0.0) ; extra == "jwt" or extra == "auth-app" or extra == "auth" or extra == "all"
Requires-Dist: anyio (>=3.6.1,<4.0.0) ; extra == "auth-oauth-device" or extra == "auth" or extra == "all"
Requires-Dist: httpx (>=0.23.0,<1.0.0)
Requires-Dist: pydantic (>=1.9.1,<2.0.0)
Requires-Dist: typing-extensions (>=4.3.0,<5.0.0)
Project-URL: Documentation, https://github.com/yanyongyu/githubkit
Project-URL: Repository, https://github.com/yanyongyu/githubkit
